geoparquet_tools/__init__.py
geoparquet_tools/cli.py
geoparquet_tools-0.1.0.dist-info/METADATA
geoparquet_tools-0.1.0.dist-info/WHEEL
geoparquet_tools-0.1.0.dist-info/entry_points.txt
geoparquet_tools-0.1.0.dist-info/top_level.txt
geoparquet_tools-0.1.0.dist-info/RECORD
