Metadata-Version: 2.2
Name: geoparquet-tools
Version: 0.1.0
Summary: Simple command-line tool for reading GeoParquet files
Classifier: Programming Language :: Python :: 3
Classifier: License :: OSI Approved :: MIT License
Classifier: Operating System :: OS Independent
Requires-Python: >=3.7
Requires-Dist: click>=8.0.0
Requires-Dist: geopandas>=0.10.0
Requires-Dist: pyarrow>=5.0.0
